<annotation>
	<folder>photos</folder>
	<filename>images (4).jpg</filename>
	<path>C:\Users\vidya\Downloads\Telegram Desktop\ChatExport_2020-09-30\photos\images (4).jpg</path>
	<source>
		<database>Unknown</database>
	</source>
	<size>
		<width>275</width>
		<height>183</height>
		<depth>3</depth>
	</size>
	<segmented>0</segmented>
	<object>
		<name>defected</name>
		<pose>Unspecified</pose>
		<truncated>1</truncated>
		<difficult>0</difficult>
		<bndbox>
			<xmin>73</xmin>
			<ymin>23</ymin>
			<xmax>194</xmax>
			<ymax>183</ymax>
		</bndbox>
	</object>
</annotation>
