<annotation>
	<folder>more</folder>
	<filename>IMG_3054.JPG</filename>
	<path>C:\Users\vidya\Desktop\more\IMG_3054.JPG</path>
	<source>
		<database>Unknown</database>
	</source>
	<size>
		<width>3264</width>
		<height>2448</height>
		<depth>3</depth>
	</size>
	<segmented>0</segmented>
	<object>
		<name>defected</name>
		<pose>Unspecified</pose>
		<truncated>1</truncated>
		<difficult>0</difficult>
		<bndbox>
			<xmin>1836</xmin>
			<ymin>370</ymin>
			<xmax>3264</xmax>
			<ymax>2046</ymax>
		</bndbox>
	</object>
	<object>
		<name>glove</name>
		<pose>Unspecified</pose>
		<truncated>0</truncated>
		<difficult>0</difficult>
		<bndbox>
			<xmin>72</xmin>
			<ymin>626</ymin>
			<xmax>2032</xmax>
			<ymax>1746</ymax>
		</bndbox>
	</object>
</annotation>
